omniparse_client/__init__.py
omniparse_client/omniparse.py
omniparse_client/utils.py
omniparse_client-0.0.1.dist-info/METADATA
omniparse_client-0.0.1.dist-info/WHEEL
omniparse_client-0.0.1.dist-info/RECORD
